LICENSE
MANIFEST.in
README.rst
setup.py
treecompare/__init__.py
treecompare/differ.py
treecompare/difference.py
treecompare/implementations.py
treecompare/xml.py
treecompare.egg-info/PKG-INFO
treecompare.egg-info/SOURCES.txt
treecompare.egg-info/dependency_links.txt
treecompare.egg-info/requires.txt
treecompare.egg-info/top_level.txt