Metadata-Version: 1.0
Name: treecompare
Version: 1.0
Summary: 
Home-page: https://github.com/rubyruy/treecompare
Author: Ruy Asan
Author-email: ruyasan@gmail.com
License: UNKNOWN
Platform: UNKNOWN
Classifier: Programming Language :: Python
Classifier: License :: OSI Approved :: BSD License
Classifier: Operating System :: OS Independent
Classifier: Development Status :: 5 - Production/Stable
Classifier: Intended Audience :: Developers
Classifier: Topic :: Software Development :: Testing
Classifier: Topic :: Software Development :: Libraries :: Python Modules
